DeepLearningWithKerasAndTensorflow/README.md
DeepLearningWithKerasAndTensorflow/__init__.py
DeepLearningWithKerasAndTensorflow/__main__.py
DeepLearningWithKerasAndTensorflow/file.epub
DeepLearningWithKerasAndTensorflow/index.html
DeepLearningWithKerasAndTensorflow/css/__init__.py
DeepLearningWithKerasAndTensorflow/css/annotations.css
DeepLearningWithKerasAndTensorflow/css/main.css
DeepLearningWithKerasAndTensorflow/css/normalize.css
DeepLearningWithKerasAndTensorflow/css/popup.css
DeepLearningWithKerasAndTensorflow/font/__init__.py
DeepLearningWithKerasAndTensorflow/font/fontello.eot
DeepLearningWithKerasAndTensorflow/font/fontello.svg
DeepLearningWithKerasAndTensorflow/font/fontello.ttf
DeepLearningWithKerasAndTensorflow/font/fontello.woff
DeepLearningWithKerasAndTensorflow/img/__init__.py
DeepLearningWithKerasAndTensorflow/img/annotator-glyph-sprite.png
DeepLearningWithKerasAndTensorflow/img/annotator-icon-sprite.png
DeepLearningWithKerasAndTensorflow/img/apple-touch-icon.png
DeepLearningWithKerasAndTensorflow/img/cancelfullscreen.png
DeepLearningWithKerasAndTensorflow/img/close.png
DeepLearningWithKerasAndTensorflow/img/fullscreen.png
DeepLearningWithKerasAndTensorflow/img/loader.gif
DeepLearningWithKerasAndTensorflow/img/menu-icon.png
DeepLearningWithKerasAndTensorflow/img/save.png
DeepLearningWithKerasAndTensorflow/img/saved.png
DeepLearningWithKerasAndTensorflow/img/settings-s.png
DeepLearningWithKerasAndTensorflow/img/settings.png
DeepLearningWithKerasAndTensorflow/img/star.png
DeepLearningWithKerasAndTensorflow/js/__init__.py
DeepLearningWithKerasAndTensorflow/js/epub.js
DeepLearningWithKerasAndTensorflow/js/epub.min.js
DeepLearningWithKerasAndTensorflow/js/epub.min.map
DeepLearningWithKerasAndTensorflow/js/hooks.min.js
DeepLearningWithKerasAndTensorflow/js/hooks.min.map
DeepLearningWithKerasAndTensorflow/js/reader.js
DeepLearningWithKerasAndTensorflow/js/reader.js.map
DeepLearningWithKerasAndTensorflow/js/reader.min.js
deep_learning_with_keras_and_tensorflow-2024.3.4.0.dist-info/METADATA
deep_learning_with_keras_and_tensorflow-2024.3.4.0.dist-info/WHEEL
deep_learning_with_keras_and_tensorflow-2024.3.4.0.dist-info/entry_points.txt
deep_learning_with_keras_and_tensorflow-2024.3.4.0.dist-info/top_level.txt
deep_learning_with_keras_and_tensorflow-2024.3.4.0.dist-info/RECORD
